enventory/__init__.py
enventory/env.py
enventory-0.0.1.dist-info/METADATA
enventory-0.0.1.dist-info/WHEEL
enventory-0.0.1.dist-info/top_level.txt
enventory-0.0.1.dist-info/RECORD
