Metadata-Version: 2.4
Name: enventory
Version: 0.0.1
Summary: Simple python dotenv utility wrapper
Author: Bec
Requires-Python: >=3.8
Requires-Dist: python-dotenv>=1.0.0
Dynamic: author
Dynamic: requires-dist
Dynamic: requires-python
Dynamic: summary
